CHANGES.txt
README.txt
bootstrap.py
buildout.cfg
setup.py
src/hurry/__init__.py
src/hurry.jqueryform.egg-info/PKG-INFO
src/hurry.jqueryform.egg-info/SOURCES.txt
src/hurry.jqueryform.egg-info/dependency_links.txt
src/hurry.jqueryform.egg-info/entry_points.txt
src/hurry.jqueryform.egg-info/namespace_packages.txt
src/hurry.jqueryform.egg-info/not-zip-safe
src/hurry.jqueryform.egg-info/requires.txt
src/hurry.jqueryform.egg-info/top_level.txt
src/hurry/jqueryform/__init__.py
src/hurry/jqueryform/jqueryform.txt
src/hurry/jqueryform/tests.py
src/hurry/jqueryform/jqueryform-build/jquery.form.js
src/hurry/jqueryform/jqueryform-build/jquery.form.min.js