Metadata-Version: 1.0
Name: hurry.jqueryform
Version: 2.47.1
Summary: hurry.resource style resources for jQuery Form Plugin.
Home-page: UNKNOWN
Author: Martijn Faassen
Author-email: faassen@startifact.com
License: MIT
Keywords: hurry.resource jquery
Platform: UNKNOWN
